plotlywrap/__init__.py
plotlywrap/figgrid.py
plotlywrap/figwrap.py
plotlywrap-0.1.0.dist-info/LICENSE
plotlywrap-0.1.0.dist-info/METADATA
plotlywrap-0.1.0.dist-info/WHEEL
plotlywrap-0.1.0.dist-info/top_level.txt
plotlywrap-0.1.0.dist-info/RECORD
