Metadata-Version: 2.1
Name: plotlywrap
Version: 0.1.0
Summary: Wrapper code to generate pixel-perfect publication qualityplots with Plotly.py.
Home-page: UNKNOWN
Author: Adam J Plowman
Author-email: UNKNOWN
License: UNKNOWN
Platform: UNKNOWN
Classifier: Development Status :: 3 - Alpha
Classifier: Intended Audience :: Science/Research
Classifier: Topic :: Scientific/Engineering :: Visualization
Requires-Dist: numpy
Requires-Dist: plotly (>=3.4.1)
Requires-Dist: ipywidgets
